crx3/__init__.py
crx3/__version__.py
crx3/common.py
crx3/creator.py
crx3/crx3_pb2.py
crx3/crx3_pb2.pyi
crx3/crx_info.py
crx3/crxfile.py
crx3/exceptions.py
crx3/id_util.py
crx3/key_util.py
crx3/utils.py
crx3/verifier.py
crx3/cli/__init__.py
crx3/cli/argparser.py
crx3/cli/cmd_create.py
crx3/cli/cmd_verify.py
crx3/cli/main.py
crx3-0.0.4.dist-info/LICENSE
crx3-0.0.4.dist-info/METADATA
crx3-0.0.4.dist-info/WHEEL
crx3-0.0.4.dist-info/entry_points.txt
crx3-0.0.4.dist-info/top_level.txt
crx3-0.0.4.dist-info/RECORD
