Metadata-Version: 2.1
Name: crx3
Version: 0.0.4
Summary: Chrome extension (crx) packaging & parsing library.
Home-page: https://github.com/liying2008/python-crx3
Author: liying
Author-email: liruoer2008@yeah.net
License: MIT
Project-URL: Bug Reports, https://github.com/liying2008/python-crx3/issues
Project-URL: Source Code, https://github.com/liying2008/python-crx3
Keywords: crx chrome edge extension
Platform: unix
Platform: linux
Platform: osx
Platform: cygwin
Platform: win32
Classifier: Development Status :: 4 - Beta
Classifier: Environment :: Console
Classifier: Intended Audience :: Developers
Classifier: License :: OSI Approved :: MIT License
Classifier: Operating System :: OS Independent
Classifier: Programming Language :: Python
Classifier: Programming Language :: Python :: 3
Classifier: Programming Language :: Python :: 3 :: Only
Classifier: Programming Language :: Python :: 3.7
Classifier: Programming Language :: Python :: 3.8
Classifier: Programming Language :: Python :: 3.9
Classifier: Programming Language :: Python :: 3.10
Classifier: Programming Language :: Python :: 3.11
Classifier: Programming Language :: Python :: 3.12
Classifier: Programming Language :: Python :: 3.13
Classifier: Topic :: Software Development :: Build Tools
Classifier: Topic :: Utilities
Requires-Python: >=3.7
License-File: LICENSE
Requires-Dist: cryptography>=40.0.2
Requires-Dist: protobuf>=3.19.6
